stactools/core/__init__.py
stactools/core/copy.py
stactools/core/layout.py
stactools/core/merge.py
stactools/core/projection.py
stactools/core/version.py
stactools/core/io/__init__.py
stactools/core/io/xml.py
stactools/core/utils/__init__.py
stactools/core/utils/convert.py
stactools/core/utils/subprocess.py
stactools_core-0.1.6.dist-info/METADATA
stactools_core-0.1.6.dist-info/WHEEL
stactools_core-0.1.6.dist-info/top_level.txt
stactools_core-0.1.6.dist-info/RECORD
